[
  {
    "inputs": [],
    "stateMutability": "nonpayable",
    "type": "constructor"
  },
  {
    "anonymous": false,
    "inputs": [
      {
        "indexed": true,
        "internalType": "uint256",
        "name": "id",
        "type": "uint256"
      },
      {
        "indexed": true,
        "internalType": "address[]",
        "name": "newAddresses",
        "type": "address[]"
      }
    ],
    "name": "AvatarAddressAdded",
    "type": "event"
  },
  {
    "anonymous": false,
    "inputs": [
      {
        "indexed": true,
        "internalType": "uint256",
        "name": "avatarID",
        "type": "uint256"
      },
      {
        "indexed": true,
        "internalType": "string",
        "name": "name",
        "type": "string"
      },
      {
        "indexed": true,
        "internalType": "string",
        "name": "aka",
        "type": "string"
      },
      {
        "indexed": false,
        "internalType": "string",
        "name": "bio",
        "type": "string"
      },
      {
        "indexed": false,
        "internalType": "string",
        "name": "avatar",
        "type": "string"
      }
    ],
    "name": "AvatarCreated",
    "type": "event"
  },
  {
    "anonymous": false,
    "inputs": [
      {
        "indexed": true,
        "internalType": "uint256",
        "name": "avatarID",
        "type": "uint256"
      },
      {
        "indexed": true,
        "internalType": "uint256",
        "name": "newMetaLinkID",
        "type": "uint256"
      },
      {
        "indexed": true,
        "internalType": "string",
        "name": "name",
        "type": "string"
      },
      {
        "indexed": false,
        "internalType": "string",
        "name": "aka",
        "type": "string"
      },
      {
        "indexed": false,
        "internalType": "string",
        "name": "universe",
        "type": "string"
      },
      {
        "indexed": false,
        "internalType": "string",
        "name": "link",
        "type": "string"
      },
      {
        "indexed": false,
        "internalType": "string",
        "name": "avatar",
        "type": "string"
      },
      {
        "indexed": false,
        "internalType": "bool",
        "name": "active",
        "type": "bool"
      }
    ],
    "name": "MetaLinkAdded",
    "type": "event"
  },
  {
    "anonymous": false,
    "inputs": [
      {
        "indexed": true,
        "internalType": "address",
        "name": "previousOwner",
        "type": "address"
      },
      {
        "indexed": true,
        "internalType": "address",
        "name": "newOwner",
        "type": "address"
      }
    ],
    "name": "OwnershipTransferred",
    "type": "event"
  },
  {
    "inputs": [
      {
        "internalType": "address[]",
        "name": "addresses",
        "type": "address[]"
      }
    ],
    "name": "addAvatarAddress",
    "outputs": [
      {
        "internalType": "bool",
        "name": "",
        "type": "bool"
      }
    ],
    "stateMutability": "nonpayable",
    "type": "function"
  },
  {
    "inputs": [
      {
        "internalType": "string",
        "name": "name",
        "type": "string"
      },
      {
        "internalType": "string",
        "name": "aka",
        "type": "string"
      },
      {
        "internalType": "string",
        "name": "universe",
        "type": "string"
      },
      {
        "internalType": "string",
        "name": "avatar",
        "type": "string"
      },
      {
        "internalType": "string",
        "name": "link",
        "type": "string"
      },
      {
        "internalType": "bool",
        "name": "active",
        "type": "bool"
      }
    ],
    "name": "addMetaLinkMetalink",
    "outputs": [
      {
        "internalType": "bool",
        "name": "",
        "type": "bool"
      }
    ],
    "stateMutability": "nonpayable",
    "type": "function"
  },
  {
    "inputs": [
      {
        "internalType": "address",
        "name": "",
        "type": "address"
      }
    ],
    "name": "addressesToMID",
    "outputs": [
      {
        "internalType": "uint256",
        "name": "",
        "type": "uint256"
      }
    ],
    "stateMutability": "view",
    "type": "function"
  },
  {
    "inputs": [
      {
        "internalType": "string",
        "name": "name",
        "type": "string"
      },
      {
        "internalType": "string",
        "name": "aka",
        "type": "string"
      },
      {
        "internalType": "string",
        "name": "bio",
        "type": "string"
      },
      {
        "internalType": "string",
        "name": "avatar",
        "type": "string"
      }
    ],
    "name": "createAvatar",
    "outputs": [
      {
        "internalType": "uint256",
        "name": "",
        "type": "uint256"
      }
    ],
    "stateMutability": "nonpayable",
    "type": "function"
  },
  {
    "inputs": [
      {
        "internalType": "uint256",
        "name": "id",
        "type": "uint256"
      }
    ],
    "name": "getAvatar",
    "outputs": [
      {
        "internalType": "string",
        "name": "",
        "type": "string"
      },
      {
        "internalType": "string",
        "name": "",
        "type": "string"
      },
      {
        "internalType": "string",
        "name": "",
        "type": "string"
      },
      {
        "internalType": "string",
        "name": "",
        "type": "string"
      },
      {
        "internalType": "uint256[]",
        "name": "links",
        "type": "uint256[]"
      }
    ],
    "stateMutability": "view",
    "type": "function"
  },
  {
    "inputs": [
      {
        "internalType": "address",
        "name": "addrss",
        "type": "address"
      }
    ],
    "name": "getAvatarID",
    "outputs": [
      {
        "internalType": "uint256",
        "name": "",
        "type": "uint256"
      }
    ],
    "stateMutability": "view",
    "type": "function"
  },
  {
    "inputs": [],
    "name": "getMyAvatarID",
    "outputs": [
      {
        "internalType": "uint256",
        "name": "",
        "type": "uint256"
      }
    ],
    "stateMutability": "view",
    "type": "function"
  },
  {
    "inputs": [
      {
        "internalType": "uint256",
        "name": "",
        "type": "uint256"
      }
    ],
    "name": "midsToAvatars",
    "outputs": [
      {
        "internalType": "string",
        "name": "name",
        "type": "string"
      },
      {
        "internalType": "string",
        "name": "aka",
        "type": "string"
      },
      {
        "internalType": "string",
        "name": "bio",
        "type": "string"
      },
      {
        "internalType": "string",
        "name": "avatar",
        "type": "string"
      }
    ],
    "stateMutability": "view",
    "type": "function"
  },
  {
    "inputs": [
      {
        "internalType": "uint256",
        "name": "",
        "type": "uint256"
      }
    ],
    "name": "midsToMetaLinks",
    "outputs": [
      {
        "internalType": "string",
        "name": "name",
        "type": "string"
      },
      {
        "internalType": "string",
        "name": "aka",
        "type": "string"
      },
      {
        "internalType": "string",
        "name": "universe",
        "type": "string"
      },
      {
        "internalType": "string",
        "name": "link",
        "type": "string"
      },
      {
        "internalType": "string",
        "name": "avatar",
        "type": "string"
      },
      {
        "internalType": "bool",
        "name": "active",
        "type": "bool"
      }
    ],
    "stateMutability": "view",
    "type": "function"
  },
  {
    "inputs": [],
    "name": "owner",
    "outputs": [
      {
        "internalType": "address",
        "name": "",
        "type": "address"
      }
    ],
    "stateMutability": "view",
    "type": "function"
  },
  {
    "inputs": [],
    "name": "renounceOwnership",
    "outputs": [],
    "stateMutability": "nonpayable",
    "type": "function"
  },
  {
    "inputs": [],
    "name": "totalAvatars",
    "outputs": [
      {
        "internalType": "uint256",
        "name": "",
        "type": "uint256"
      }
    ],
    "stateMutability": "view",
    "type": "function"
  },
  {
    "inputs": [],
    "name": "totalMetaLinks",
    "outputs": [
      {
        "internalType": "uint256",
        "name": "",
        "type": "uint256"
      }
    ],
    "stateMutability": "view",
    "type": "function"
  },
  {
    "inputs": [
      {
        "internalType": "address",
        "name": "newOwner",
        "type": "address"
      }
    ],
    "name": "transferOwnership",
    "outputs": [],
    "stateMutability": "nonpayable",
    "type": "function"
  }
]